maxar_platform/__init__.py
maxar_platform/api_keys.py
maxar_platform/discovery.py
maxar_platform/exceptions.py
maxar_platform/monitoring.py
maxar_platform/ogc/__init__.py
maxar_platform/ogc/footprints.py
maxar_platform/ogc/imagery.py
maxar_platform/ogc/seamlines.py
maxar_platform/ordering.py
maxar_platform/raster_analytics.py
maxar_platform/session.py
maxar_platform/tasking.py
maxar_platform/usage.py
maxar_platform-1.0.7.dist-info/LICENSE.txt
maxar_platform-1.0.7.dist-info/METADATA
maxar_platform-1.0.7.dist-info/WHEEL
maxar_platform-1.0.7.dist-info/RECORD
