Metadata-Version: 2.1
Name: maxar-platform
Version: 1.0.7
Summary: Maxar Geospatial Platform SDK
License: MIT
Author: Marc Pfister
Author-email: marc.pfister@maxar.com
Requires-Python: >=3.9,<4.0
Classifier: License :: OSI Approved :: MIT License
Classifier: Programming Language :: Python :: 3
Classifier: Programming Language :: Python :: 3.9
Classifier: Programming Language :: Python :: 3.10
Classifier: Programming Language :: Python :: 3.11
Classifier: Programming Language :: Python :: 3.12
Provides-Extra: rasterio
Requires-Dist: OWSLib (>=0.29.0,<0.30.0)
Requires-Dist: affine (>=2.4.0,<3.0.0)
Requires-Dist: pendulum (>=3.0.0,<4.0.0)
Requires-Dist: pygeofilter (>=0.2.0,<0.3.0)
Requires-Dist: pyproj (>=3.6.0,<4.0.0)
Requires-Dist: pystac-client (>=0.7,<1.0)
Requires-Dist: rasterio (>=1.3.0,<2.0.0) ; extra == "rasterio"
Requires-Dist: requests (>=2.31.0,<3.0.0)
Requires-Dist: requests-oauthlib (>=2.0.0,<3.0.0)
Project-URL: Documentation, https://developers.maxar.com/docs/developer-tools/python-sdk
